{
  "audit": {
    "trackChanges": true
  },
  "canonVersion": "1.0.0",
  "childTables": [],
  "doctypeId": "erpnext:Accounts:Allowed Dimension",
  "events": [
    {
      "event": "validate",
      "handlers": [
        "erpnext.support.doctype.service_level_agreement.service_level_agreement.apply",
        "erpnext.setup.doctype.transaction_deletion_record.transaction_deletion_record.check_for_running_deletion_job"
      ],
      "handlersParsed": [
        {
          "attrPath": "apply",
          "module": "erpnext.support.doctype.service_level_agreement.service_level_agreement"
        },
        {
          "attrPath": "check_for_running_deletion_job",
          "module": "erpnext.setup.doctype.transaction_deletion_record.transaction_deletion_record"
        }
      ]
    }
  ],
  "fieldOrder": [
    "accounting_dimension",
    "dimension_value"
  ],
  "fields": [
    {
      "constraints": {},
      "fieldname": "accounting_dimension",
      "fieldtype": "link",
      "label": "Accounting Dimension",
      "optionsParsed": {
        "kind": "link",
        "target": "DocType"
      },
      "optionsRaw": "DocType",
      "permlevel": 0,
      "ref": {
        "doctype": "DocType",
        "kind": "static"
      },
      "requiredStatic": false,
      "ui": {
        "readOnly": true
      },
      "unique": false
    },
    {
      "constraints": {},
      "fieldname": "dimension_value",
      "fieldtype": "dynamic_link",
      "optionsRaw": "accounting_dimension",
      "permlevel": 0,
      "ref": {
        "doctypeField": "accounting_dimension",
        "kind": "dynamic"
      },
      "requiredStatic": false,
      "ui": {
        "inListView": true
      },
      "unique": false
    }
  ],
  "identity": {
    "app": "erpnext",
    "isSingle": false,
    "isSubmittable": false,
    "isTree": false,
    "module": "Accounts",
    "naming": {
      "strategy": "hash"
    }
  },
  "name": "Allowed Dimension",
  "permissions": [],
  "ui": {
    "searchFields": [],
    "showNameInGlobalSearch": false,
    "sortField": "creation",
    "sortOrder": "DESC"
  },
  "workflows": [
    {
      "kind": "unavailable"
    }
  ]
}